range_ex/__init__.py
range_ex/range_regex.py
range_ex-0.0.2.dist-info/licenses/LICENSE
range_ex-0.0.2.dist-info/METADATA
range_ex-0.0.2.dist-info/WHEEL
range_ex-0.0.2.dist-info/top_level.txt
range_ex-0.0.2.dist-info/RECORD
