Metadata-Version: 2.4
Name: range_ex
Version: 0.0.2
Summary: Generate regex for numerical ranges
Author-email: Niels Mündler <n.muendler@posteo.de>, Raj Kiran P <rajkiranjp@gmail.com>
License: MIT
Project-URL: Homepage, https://github.com/nielstron/range_ex
Project-URL: Repository, https://github.com/nielstron/range_ex
Classifier: Programming Language :: Python :: 3
Classifier: Programming Language :: Python :: 3.10
Classifier: Programming Language :: Python :: 3.11
Classifier: Programming Language :: Python :: 3.12
Classifier: License :: OSI Approved :: MIT License
Classifier: Operating System :: OS Independent
Classifier: Development Status :: 4 - Beta
Requires-Python: >=3.10
License-File: LICENSE
Provides-Extra: dev
Requires-Dist: pytest; extra == "dev"
Requires-Dist: pytest-xdist; extra == "dev"
Requires-Dist: hypothesis; extra == "dev"
Dynamic: license-file
